sport_activities_features_gui/__init__.py
sport_activities_features_gui/global_vars.py
sport_activities_features_gui/logic/__init__.py
sport_activities_features_gui/logic/graphs.py
sport_activities_features_gui/logic/import_data.py
sport_activities_features_gui/logic/multi_thread.py
sport_activities_features_gui/logic/transformations.py
sport_activities_features_gui/main.py
sport_activities_features_gui/media/Icon.png
sport_activities_features_gui/models/__init__.py
sport_activities_features_gui/models/user.py
sport_activities_features_gui/styles.qss
sport_activities_features_gui/widgets/__init__.py
sport_activities_features_gui/widgets/calendar_widget.py
sport_activities_features_gui/widgets/graphs_widget.py
sport_activities_features_gui/widgets/import_data_widget.py
sport_activities_features_gui/widgets/transformations_widget.py
sport_activities_features_gui/windows/__init__.py
sport_activities_features_gui/windows/add_profile.py
sport_activities_features_gui/windows/main_window.py
sport_activities_features_gui/windows/profiles_window.py
sport_activities_features_gui/windows/view_attributes_window.py
sport_activities_features_gui-0.4.0.dist-info/AUTHORS.md
sport_activities_features_gui-0.4.0.dist-info/LICENSE
sport_activities_features_gui-0.4.0.dist-info/METADATA
sport_activities_features_gui-0.4.0.dist-info/WHEEL
sport_activities_features_gui-0.4.0.dist-info/entry_points.txt
sport_activities_features_gui-0.4.0.dist-info/RECORD
