Metadata-Version: 2.1
Name: sport-activities-features-gui
Version: 0.4.0
Summary: GUI for sport-activities-features package
Home-page: https://github.com/firefly-cpp/sport-activities-features-gui
Keywords: computational intelligence,cycling,data mining,datasets,gpx,gui,optimization,sport activities,tcx
Author: otiv33
Author-email: vito.abeln@gmail.com
Requires-Python: >=3.10,<4.0
Classifier: Programming Language :: Python :: 3
Classifier: Programming Language :: Python :: 3.10
Classifier: Programming Language :: Python :: 3.11
Classifier: Programming Language :: Python :: 3.12
Requires-Dist: PyQt6 (>=6.5.1,<7.0.0)
Requires-Dist: QtAwesome (>=1.2.1,<2.0.0)
Requires-Dist: opencv-python-headless (>=4.8.0.74,<5.0.0.0)
Requires-Dist: sip (>=6.7.9,<7.0.0)
Requires-Dist: sport-activities-features (>=0.5.0,<0.6.0)
Project-URL: Repository, https://github.com/firefly-cpp/sport-activities-features-gui
